hostbutter/__init__.py
hostbutter/__main__.py
hostbutter/__version__.py
hostbutter/constants.py
hostbutter/exceptions.py
hostbutter/py.typed
hostbutter/query.py
hostbutter/utils.py
hostbutter/__pycache__/__init__.cpython-310.pyc
hostbutter/__pycache__/__main__.cpython-310.pyc
hostbutter/__pycache__/__version__.cpython-310.pyc
hostbutter/__pycache__/constants.cpython-310.pyc
hostbutter/__pycache__/exceptions.cpython-310.pyc
hostbutter/__pycache__/query.cpython-310.pyc
hostbutter/__pycache__/utils.cpython-310.pyc
hostbutter/collections/requirements.yml
hostbutter/collections/ansible_collections/fresh2dev/hostbutter/README.md
hostbutter/collections/ansible_collections/fresh2dev/hostbutter/galaxy.yml
hostbutter/collections/ansible_collections/fresh2dev/hostbutter/meta/runtime.yml
hostbutter/collections/ansible_collections/fresh2dev/hostbutter/playbooks/apply_ssh.yml
hostbutter/collections/ansible_collections/fresh2dev/hostbutter/playbooks/apply_swarm.yml
hostbutter/collections/ansible_collections/fresh2dev/hostbutter/playbooks/reboot_swarm.yml
hostbutter/collections/ansible_collections/fresh2dev/hostbutter/playbooks/upgrade_swarm.yml
hostbutter/collections/ansible_collections/fresh2dev/hostbutter/roles/swarmcluster/defaults/main.yml
hostbutter/collections/ansible_collections/fresh2dev/hostbutter/roles/swarmcluster/handlers/main.yml
hostbutter/collections/ansible_collections/fresh2dev/hostbutter/roles/swarmcluster/meta/main.yml
hostbutter/collections/ansible_collections/fresh2dev/hostbutter/roles/swarmcluster/tasks/apply-cacert.yml
hostbutter/collections/ansible_collections/fresh2dev/hostbutter/roles/swarmcluster/tasks/apply-dns-systemd.yml
hostbutter/collections/ansible_collections/fresh2dev/hostbutter/roles/swarmcluster/tasks/apply-dnsmasq.yml
hostbutter/collections/ansible_collections/fresh2dev/hostbutter/roles/swarmcluster/tasks/apply-fail2ban.yml
hostbutter/collections/ansible_collections/fresh2dev/hostbutter/roles/swarmcluster/tasks/apply-firewall.yml
hostbutter-0.0.1a5.dist-info/LICENSE
hostbutter-0.0.1a5.dist-info/METADATA
hostbutter-0.0.1a5.dist-info/WHEEL
hostbutter-0.0.1a5.dist-info/entry_points.txt
hostbutter-0.0.1a5.dist-info/top_level.txt
hostbutter-0.0.1a5.dist-info/RECORD
